[
  {
    "date": "2020-02-29",
    "events": [
      {
        "name": "event Name",
        "body": "Body event",
        "time": "12:00",
        "isIn": false
      },
      {
        "name": "event Name",
        "body": "Body event",
        "time": "17:00",
        "isIn": true
      }
    ]
  },
  {
    "date": "2020-03-01",
    "events": [
      {
        "name": "event Name",
        "body": "Body event",
        "time": "15:00",
        "isIn": false
      },
      {
        "name": "event Name",
        "body": "Body event",
        "time": "19:00",
        "isIn": true
      }
    ]
  },
  {
    "date": "2020-03-02",
    "events": [
      {
        "name": "event Name",
        "body": "Body event",
        "time": "12:00",
        "isIn": false
      },
      {
        "name": "event Name",
        "body": "Body event",
        "time": "17:00",
        "isIn": true
      }
    ]
  },
  {
    "date": "2020-03-03",
    "events": [
      {
        "name": "event Name",
        "body": "Body event",
        "time": "12:00",
        "isIn": false
      },
      {
        "name": "event Name",
        "body": "Body event",
        "time": "17:00",
        "isIn": true
      }
    ]
  },
  {
    "date": "2020-03-04",
    "events": [
      {
        "name": "event Name",
        "body": "Body event",
        "time": "12:00",
        "isIn": false
      },
      {
        "name": "event Name",
        "body": "Body event",
        "time": "17:00",
        "isIn": true
      }
    ]
  },
  {
    "date": "2020-03-05",
    "events": [
      {
        "name": "event Name",
        "body": "Body event",
        "time": "12:00",
        "isIn": false
      },
      {
        "name": "event Name",
        "body": "Body event",
        "time": "17:00",
        "isIn": true
      }
    ]
  },
  {
    "date": "2020-03-06",
    "events": [
      {
        "name": "event Name",
        "body": "Body event",
        "time": "12:00",
        "isIn": false
      },
      {
        "name": "event Name",
        "body": "Body event",
        "time": "17:00",
        "isIn": true
      }
    ]
  }
]